be_helpers/__init__.py
be_helpers/module_helper.py
be_helpers/version.py
be_helpers-0.1.0.dist-info/LICENSE.txt
be_helpers-0.1.0.dist-info/METADATA
be_helpers-0.1.0.dist-info/WHEEL
be_helpers-0.1.0.dist-info/top_level.txt
be_helpers-0.1.0.dist-info/RECORD
