Metadata-Version: 2.1
Name: be-helpers
Version: 0.1.0
Summary: Custom brainelectronics python helper modules
Home-page: https://github.com/brainelectronics/be-helpers
Author: brainelectronics
Author-email: info@brainelectronics.de
Project-URL: Bug Reports, https://github.com/brainelectronics/be-helpers/issues
Project-URL: Source, https://github.com/brainelectronics/be-helpers/
Keywords: helpers,collection
Classifier: Development Status :: 5 - Production/Stable
Classifier: Intended Audience :: Developers
Classifier: Topic :: Software Development :: Build Tools
Classifier: License :: OSI Approved :: MIT License
Classifier: Programming Language :: Python :: 3
Classifier: Programming Language :: Python :: 3.7
Classifier: Programming Language :: Python :: 3.8
Classifier: Programming Language :: Python :: 3.9
Classifier: Programming Language :: Python :: 3.10
Classifier: Programming Language :: Python :: 3 :: Only
Requires-Python: >=3.7, <4
License-File: LICENSE.txt
Requires-Dist: PyYAML (<6,>=5.4.1)
Provides-Extra: dev
Requires-Dist: tox (<4,>=3.25.1) ; extra == 'dev'
Provides-Extra: test
Requires-Dist: flake8 (<6,>=5.0.0) ; extra == 'test'
Requires-Dist: coverage (<7,>=6.4.2) ; extra == 'test'
Requires-Dist: nose2 (<1,>=0.12.0) ; extra == 'test'
